openssh_sync/__init__.py
openssh_sync/cli.py
openssh_sync/config.py
openssh_sync/downloader.py
openssh_sync/fetcher.py
openssh_sync/html_generator.py
openssh_sync/incremental_checker.py
openssh_sync/main.py
openssh_sync/systemd.py
openssh_sync/utils.py
openssh_synchronization-1.1.8.dist-info/METADATA
openssh_synchronization-1.1.8.dist-info/WHEEL
openssh_synchronization-1.1.8.dist-info/entry_points.txt
openssh_synchronization-1.1.8.dist-info/licenses/LICENSE
openssh_synchronization-1.1.8.dist-info/RECORD
