Metadata-Version: 2.4
Name: openssh-synchronization
Version: 1.1.8
Summary: OpenSSH resource synchronization tool for Aliyun mirrors
Project-URL: Homepage, https://gitee.com/liumou_site/openssh-synchronization
Project-URL: Repository, https://gitee.com/liumou_site/openssh-synchronization
Project-URL: Documentation, https://gitee.com/liumou_site/openssh-synchronization#readme
Author-email: 坐公交也用券 <liumou.site@qq.com>
License:                                  Apache License
License-File: LICENSE
Keywords: aliyun,mirror,openssh,synchronization
Classifier: Development Status :: 4 - Beta
Classifier: Intended Audience :: System Administrators
Classifier: License :: OSI Approved :: MIT License
Classifier: Operating System :: OS Independent
Classifier: Programming Language :: Python :: 3
Classifier: Programming Language :: Python :: 3.7
Classifier: Programming Language :: Python :: 3.8
Classifier: Programming Language :: Python :: 3.9
Classifier: Programming Language :: Python :: 3.10
Classifier: Programming Language :: Python :: 3.11
Classifier: Programming Language :: Python :: 3.12
Requires-Python: >=3.7
Requires-Dist: beautifulsoup4>=4.9.0
Requires-Dist: click>=8.0.0
Requires-Dist: plsm>=1.0.0
Requires-Dist: requests>=2.25.0
Provides-Extra: dev
Requires-Dist: black>=21.0.0; extra == 'dev'
Requires-Dist: flake8>=3.9.0; extra == 'dev'
Requires-Dist: isort>=5.0.0; extra == 'dev'
Requires-Dist: pytest-cov>=2.0.0; extra == 'dev'
Requires-Dist: pytest>=6.0.0; extra == 'dev'
